Metadata-Version: 2.1
Name: tindetheus
Version: 1.0.2
Summary: Build personalized machine learning models for Tinder based on your historical preference
Home-page: https://github.com/cjekel/tindetheus
Author: Charles Jekel
Author-email: cjekel@gmail.com
License: MIT License
Platform: any
